dryer/__init__.py
dryer/_version.py
dryer/bases.py
dryer/coercible.py
dryer/json.py
dryer/schema.py
dryer/strict.py
dryer/utils.py
dryer-1.0a1.dist-info/DESCRIPTION.rst
dryer-1.0a1.dist-info/METADATA
dryer-1.0a1.dist-info/RECORD
dryer-1.0a1.dist-info/WHEEL
dryer-1.0a1.dist-info/metadata.json
dryer-1.0a1.dist-info/top_level.txt
