Metadata-Version: 2.0
Name: dryer
Version: 1.0a1
Summary: coerce and serialize data structures
Home-page: http://py.errorist.io/dryer
Author: UNKNOWN
Author-email: UNKNOWN
License: MIT
Keywords: serialization
Platform: UNKNOWN
Classifier: Development Status :: 5 - Production/Stable
Classifier: Intended Audience :: Developers
Classifier: License :: OSI Approved :: MIT License
Classifier: Operating System :: OS Independent
Classifier: Programming Language :: Python :: 3
Classifier: Programming Language :: Python :: 3.6
Classifier: Topic :: Software Development :: Libraries
Classifier: Topic :: Software Development :: Libraries :: Python Modules
